[
    {
        "id": "d0891740-f138-11eb-b1fd-f9217d241c0a",
        "name": "Илья",
        "description": "Горбатый лучший в мире",
        "status": false,
        "created": 1627651188405
    },
    {
        "id": "781aaa30-f13b-11eb-8dc3-d98d0974155e",
        "name": "Илья",
        "description": "Горбатый лучший в мире",
        "status": false,
        "created": 1627652328531
    },
    {
        "id": "83846af0-f13b-11eb-a54e-958d4f302111",
        "name": "Влад модиф.",
        "description": "~",
        "status": false,
        "created": 1627652347679
    },
    {
        "id": "987fdba0-f13c-11eb-b9eb-798a962fa71f",
        "name": "Влад",
        "description": "Кто я?",
        "status": false,
        "created": 1627652812379
    }
]